README.md
pyproject.toml
setup.cfg
setup.py
django_address/__init__.py
django_address/admin.py
django_address/apps.py
django_address/base_models.py
django_address/fields.py
django_address/models.py
django_address/service.py
django_address/migrations/0001_initial.py
django_address/migrations/__init__.py
django_address_app.egg-info/PKG-INFO
django_address_app.egg-info/SOURCES.txt
django_address_app.egg-info/dependency_links.txt
django_address_app.egg-info/requires.txt
django_address_app.egg-info/top_level.txt