Metadata-Version: 2.1
Name: django-address-app
Version: 0.1.13
Summary: Django models for storing and retrieving postal addresses.
Home-page: https://github.com/onufrienkovi/django-address-app
Author: Vyacheslav Onufrienko
Author-email: onufrienkovi@gmail.com
License: UNKNOWN
Platform: UNKNOWN
Classifier: Environment :: Web Environment
Classifier: Framework :: Django
Classifier: Intended Audience :: Developers
Classifier: Operating System :: OS Independent
Classifier: Programming Language :: Python
Classifier: Programming Language :: Python :: 3.7
Classifier: Programming Language :: Python :: 3.8
Classifier: Topic :: Internet :: WWW/HTTP
Classifier: Topic :: Software Development :: Libraries :: Application Frameworks
Classifier: Topic :: Software Development :: Libraries :: Python Modules
Requires-Python: >=3.7
Provides-Extra: test
Provides-Extra: lint
Provides-Extra: dev
